agentic_chunker/__init__.py
agentic_chunker/main.py
agentic_chunker/prompts.py
agentic_chunker/version.py
agentic_chunker-0.0.6.dist-info/LICENSE
agentic_chunker-0.0.6.dist-info/METADATA
agentic_chunker-0.0.6.dist-info/WHEEL
agentic_chunker-0.0.6.dist-info/top_level.txt
agentic_chunker-0.0.6.dist-info/RECORD
