Metadata-Version: 2.1
Name: agentic-chunker
Version: 0.0.6
Summary: A tool for improving the quality of chunks.
Author: Gurram Siddarth Reddy
License-File: LICENSE
Requires-Dist: openai>=1.24.1
Requires-Dist: tqdm>=4.11.1
